transformation/__init__.py
transformation/transformation.py
transformation3d-2.2.4.dist-info/licenses/LICENSE
transformation3d-2.2.4.dist-info/METADATA
transformation3d-2.2.4.dist-info/WHEEL
transformation3d-2.2.4.dist-info/top_level.txt
transformation3d-2.2.4.dist-info/RECORD
