Metadata-Version: 2.4
Name: transformation3d
Version: 2.2.4
Summary: An easy-to-use class representing transformations in 3D space.
Author-email: Tim Schneider <tim@robot-learning.de>
License-Expression: MIT
Project-URL: Homepage, https://github.com/TimSchneider42/python-transformation3d
License-File: LICENSE
Requires-Dist: scipy
Requires-Dist: numpy
Dynamic: license-file
